{
  "id": 9618,
  "idx": "MXO-04287",
  "title": "Звучит труба",
  "titleOriginal": "The fight is on",
  "lyrics":
  {
    "stanzas": [
      {
        "type": "stanza",
        "lines": ["Звучит труба, пора нам выступать в поход,", "Господь зовёт, к сраженью будь готов!", "Вперед, вперед! Врагов не бойся и невзгод,", "Не забывай, что воин ты Христов!"]
      },
      {
        "type": "refrain",
        "lines": ["Единодушно на пути", "Стремимся к вечной цели мы.", "Ведёт спасённых", "Превознесённый, ", "И нас не сломят силы тьмы."]
      },
      {
        "type": "stanza",
        "lines": ["Жестокий враг, но верим он не устоит.", "Мы победим - сильна Иисуса кровь.", "Христос наш Вождь, живая вера, крепкий щит,", "И всё во всём Спасителя любовь."]
      },
      {
        "type": "stanza",
        "lines": ["О человек! повержен ныне ты врагом...", "Вставай скорей, вступай в ряды Христа!", "Он ждёт тебя, поверь и помни, друг, о том,", "Что только в Нём блаженства полнота!"]
      }]
  },
  "instruments": [
    {
      "title": "Труба",
      "id": "trumpet"
    }],
  "vocals": [
    {
      "title": "Соло",
      "id": "solo"
    },
    {
      "title": "Баритон",
      "id": "solo_bariton"
    },
    {
      "title": "Молодежный хор",
      "id": "choir_youth"
    }],
  "topics": [
    {
      "title": "О Церкви",
      "id": "topic_020"
    }],
  "publishDate": "2021-12-30",
  "lyricists": [],
  "composers": [],
  "arrangers": [
    {
      "id": 4,
      "firstName": "Давид",
      "lastName": "Варкентин",
      "fullName": "Варкентин Давид",
      "fullShortName": "Варкентин Давид"
    }],
  "orchestrators": [],
  "translators": [],
  "files": [
    {
      "name": "Звучит труба - Партитура - Trumpet in Bb2",
      "format": "pdf",
      "location": "Звучит труба - Партитура - Trumpet in Bb2.pdf",
      "size": "100.2 KB"
    },
    {
      "name": "000 - Звучит труба - Хор",
      "format": "pdf",
      "location": "000 - Звучит труба - Хор.pdf",
      "size": "384.5 KB"
    },
    {
      "name": "001 - Звучит труба - Trumpet in Bb",
      "format": "pdf",
      "location": "001 - Звучит труба - Trumpet in Bb.pdf",
      "size": "101.2 KB"
    },
    {
      "name": "Звучит труба(альбом Святая Церковь)",
      "format": "mp3",
      "location": "Звучит труба(альбом Святая Церковь).mp3",
      "size": "2.9 MB"
    }],
  "thumbs": ["Звучит труба - Партитура - Trumpet in Bb2.pdf-1.jpg", "000 - Звучит труба - Хор.pdf-1.jpg", "000 - Звучит труба - Хор.pdf-2.jpg", "000 - Звучит труба - Хор.pdf-3.jpg", "000 - Звучит труба - Хор.pdf-4.jpg", "000 - Звучит труба - Хор.pdf-5.jpg", "001 - Звучит труба - Trumpet in Bb.pdf-1.jpg"],
  "state": "COMPLETED",
  "collections": [
    {
      "id": 59,
      "title": "Святая Церковь",
      "type": "disk"
    }],
  "lang": "ru",
  "createDate": "2021-10-21",
  "publishYear": 2021
}